{
  "version": 0.6,
  "generator": "Overpass API 0.7.62.4 2390de5a",
  "osm3s": {
    "timestamp_osm_base": "2024-12-15T03:51:59Z",
    "timestamp_areas_base": "2024-12-15T03:51:59Z",
    "copyright": "The data included in this document is from www.openstreetmap.org. The data is made available under ODbL."
  },
  "elements": [
    {
      "type": "node",
      "id": 1875665997,
      "lat": 15.4306552,
      "lon": 73.97157,
      "tags": {
        "name": "Shantadurga Guest House",
        "tourism": "guest_house"
      }
    },
    {
      "type": "node",
      "id": 3766893624,
      "lat": 15.3919236,
      "lon": 74.0029844,
      "tags": {
        "tourism": "hotel"
      }
    },
    {
      "type": "node",
      "id": 3766893644,
      "lat": 15.4144558,
      "lon": 73.9871632,
      "tags": {
        "name": "Farmagudi Residency",
        "tourism": "hotel"
      }
    },
    {
      "type": "node",
      "id": 4283896502,
      "lat": 15.395296,
      "lon": 74.00187,
      "tags": {
        "name": "Hill view",
        "tourism": "motel"
      }
    },
    {
      "type": "node",
      "id": 4290192992,
      "lat": 15.410502,
      "lon": 73.990514,
      "tags": {
        "name": "Classic Residency",
        "tourism": "hotel"
      }
    },
    {
      "type": "node",
      "id": 4292998189,
      "lat": 15.4009,
      "lon": 74.012814,
      "tags": {
        "name": "Hotel Top",
        "tourism": "hotel"
      }
    },
    {
      "type": "node",
      "id": 4293082810,
      "lat": 15.3999991,
      "lon": 74.0050773,
      "tags": {
        "name": "Hotel Menino",
        "tourism": "hotel"
      }
    },
    {
      "type": "node",
      "id": 4294192489,
      "lat": 15.399055,
      "lon": 74.003289,
      "tags": {
        "name": "Hotel Sungrace",
        "tourism": "hotel"
      }
    },
    {
      "type": "node",
      "id": 4317926991,
      "lat": 15.4039438,
      "lon": 73.9855443,
      "tags": {
        "name": "Sanjeevan Hostel",
        "tourism": "hostel"
      }
    },
    {
      "type": "node",
      "id": 4338270492,
      "lat": 15.419652,
      "lon": 73.980895,
      "tags": {
        "name": "Hostel D1",
        "tourism": "hostel"
      }
    },
    {
      "type": "node",
      "id": 4338337693,
      "lat": 15.420697,
      "lon": 73.98006,
      "tags": {
        "name": "GEC Girls Hostel 1",
        "tourism": "hostel"
      }
    },
    {
      "type": "way",
      "id": 169716663,
      "nodes": [
        1808788527,
        1808788525,
        1808788529,
        1808788531,
        1808788527
      ],
      "tags": {
        "name": "Sri Mahalasa Guest House",
        "tourism": "hotel"
      }
    },
    {
      "type": "way",
      "id": 430043922,
      "nodes": [
        4293092489,
        4293092490,
        4293092491,
        4293092492,
        4293092493,
        4293092494,
        4293092489
      ],
      "tags": {
        "building": "yes",
        "tourism": "hotel"
      }
    },
    {
      "type": "way",
      "id": 614018433,
      "nodes": [
        5808689099,
        5808689100,
        5808689101,
        5808689102,
        5808689103,
        5808689104,
        5808689105,
        5808689106,
        5808689107,
        5808689108,
        5808689109,
        5808689110,
        5808689111,
        5808689112,
        5808689113,
        5808689114,
        5808689099
      ],
      "tags": {
        "building": "yes",
        "tourism": "hostel"
      }
    },
    {
      "type": "way",
      "id": 614219283,
      "nodes": [
        5810338252,
        5810338253,
        5810338254,
        5810338255,
        5810338256,
        5810338257,
        5810338258,
        5810338259,
        5810338260,
        5810338261,
        5810338262,
        5810338263,
        5810338264,
        5810338265,
        5810338266,
        5810338267,
        5810338268,
        5810338252
      ],
      "tags": {
        "building": "yes",
        "name": "GEC Boys' Hostel 2",
        "tourism": "hostel"
      }
    },
    {
      "type": "way",
      "id": 614219284,
      "nodes": [
        5810338269,
        5810338270,
        5810338271,
        5810338272,
        5810338273,
        5810338274,
        5810338275,
        5810338276,
        5810338277,
        5810338278,
        5810338279,
        5810338280,
        5810338281,
        5810338282,
        5810338283,
        5810338284,
        5810338285,
        5810338286,
        5810338287,
        5810338288,
        5810338289,
        5810338269
      ],
      "tags": {
        "building": "yes",
        "tourism": "hostel"
      }
    },
    {
      "type": "way",
      "id": 614219285,
      "nodes": [
        5810338290,
        5810338291,
        5810338292,
        5810338293,
        5810338294,
        5810338295,
        5810338296,
        5810338297,
        5810338298,
        5810338299,
        5810338300,
        5810338301,
        5810338302,
        5810338303,
        5810338304,
        5810338305,
        5810338306,
        5810338307,
        5810338308,
        5810338309,
        5810338310,
        5810338311,
        5810338312,
        5810338290
      ],
      "tags": {
        "building": "yes",
        "tourism": "hostel"
      }
    },
    {
      "type": "way",
      "id": 614219286,
      "nodes": [
        5810338313,
        5810338314,
        5810338315,
        5810338316,
        5810338317,
        5810338318,
        5810338319,
        5810338320,
        5810338321,
        5810338322,
        5810338323,
        5810338324,
        5810338325,
        5810338326,
        5810338327,
        5810338328,
        5810338329,
        5810338330,
        5810338331,
        5810338332,
        5810338333,
        5810338334,
        5810338313
      ],
      "tags": {
        "building": "yes",
        "tourism": "hostel"
      }
    },
    {
      "type": "way",
      "id": 1172333687,
      "nodes": [
        10892561642,
        10892561643,
        10892561644,
        10892561645,
        10892561646,
        10892561647,
        10892561648,
        10892561655,
        10892561649,
        10892561650,
        10892561651,
        10892561652,
        10892561642
      ],
      "tags": {
        "building": "yes",
        "name": "Boys Hostel 1",
        "tourism": "hostel"
      }
    },
    {
      "type": "way",
      "id": 1172333688,
      "nodes": [
        10892561656,
        10892561657,
        10892561658,
        10892561659,
        10892561660,
        10892561661,
        10892561662,
        10892561663,
        10892561664,
        10892561665,
        10892561666,
        10892641629,
        10892561667,
        10892561668,
        10892561669,
        10892561670,
        10892561671,
        10892561672,
        10892561673,
        10892561674,
        10892561675,
        10892561676,
        10892561656
      ],
      "tags": {
        "building": "yes",
        "name": "Boys Hostel 2",
        "tourism": "hostel"
      }
    },
    {
      "type": "way",
      "id": 1183298147,
      "nodes": [
        10988315039,
        10988315040,
        10988315041,
        10988315042,
        10988315043,
        10988315044,
        10988315045,
        10988315046,
        10988315047,
        10988315048,
        10988315049,
        10988315050,
        10988315051,
        10988315052,
        10988315053,
        10988315054,
        10988315055,
        10988315056,
        10988315057,
        10988315039
      ],
      "tags": {
        "building": "yes",
        "name": "Boys Hostel 3",
        "tourism": "hostel"
      }
    },
    {
      "type": "way",
      "id": 1183298148,
      "nodes": [
        10988315058,
        10988315059,
        10988315060,
        10988315061,
        10988315062,
        10988315063,
        10988315064,
        10988315065,
        10988315066,
        10988315067,
        10988315068,
        10988315069,
        10988315070,
        10988315071,
        10988315072,
        10988315073,
        10988315074,
        10988315058
      ],
      "tags": {
        "building": "yes",
        "name": "Girls Hostel",
        "tourism": "hostel"
      }
    },
    {
      "type": "relation",
      "id": 8405828,
      "members": [
        {
          "type": "way",
          "ref": 601302469,
          "role": "outer"
        },
        {
          "type": "way",
          "ref": 601302468,
          "role": "inner"
        }
      ],
      "tags": {
        "building": "yes",
        "tourism": "hostel",
        "type": "multipolygon"
      }
    },
    {
      "type": "relation",
      "id": 8405831,
      "members": [
        {
          "type": "way",
          "ref": 601302475,
          "role": "outer"
        },
        {
          "type": "way",
          "ref": 601302478,
          "role": "outer"
        },
        {
          "type": "way",
          "ref": 601302472,
          "role": "outer"
        },
        {
          "type": "way",
          "ref": 601302474,
          "role": "outer"
        },
        {
          "type": "way",
          "ref": 601302470,
          "role": "outer"
        },
        {
          "type": "way",
          "ref": 601302476,
          "role": "inner"
        },
        {
          "type": "way",
          "ref": 601302477,
          "role": "inner"
        },
        {
          "type": "way",
          "ref": 601302471,
          "role": "inner"
        },
        {
          "type": "way",
          "ref": 601302473,
          "role": "inner"
        }
      ],
      "tags": {
        "building": "yes",
        "tourism": "hostel",
        "type": "multipolygon"
      }
    },
    {
      "type": "node",
      "id": 4293092489,
      "lat": 15.4001542,
      "lon": 74.0050505
    },
    {
      "type": "node",
      "id": 4293092490,
      "lat": 15.4000818,
      "lon": 74.0049808
    },
    {
      "type": "node",
      "id": 4293092491,
      "lat": 15.4000301,
      "lon": 74.0050317
    },
    {
      "type": "node",
      "id": 4293092492,
      "lat": 15.3999525,
      "lon": 74.0049647
    },
    {
      "type": "node",
      "id": 4293092493,
      "lat": 15.3998775,
      "lon": 74.005072
    },
    {
      "type": "node",
      "id": 4293092494,
      "lat": 15.4000482,
      "lon": 74.0052087
    },
    {
      "type": "node",
      "id": 5808689099,
      "lat": 15.4153297,
      "lon": 73.9886631
    },
    {
      "type": "node",
      "id": 5808689100,
      "lat": 15.4153876,
      "lon": 73.9887417
    },
    {
      "type": "node",
      "id": 5808689101,
      "lat": 15.4154264,
      "lon": 73.988711
    },
    {
      "type": "node",
      "id": 5808689102,
      "lat": 15.4154677,
      "lon": 73.9887671
    },
    {
      "type": "node",
      "id": 5808689103,
      "lat": 15.4152342,
      "lon": 73.988952
    },
    {
      "type": "node",
      "id": 5808689104,
      "lat": 15.4152204,
      "lon": 73.9889332
    },
    {
      "type": "node",
      "id": 5808689105,
      "lat": 15.4150737,
      "lon": 73.9890494
    },
    {
      "type": "node",
      "id": 5808689106,
      "lat": 15.4150027,
      "lon": 73.988953
    },
    {
      "type": "node",
      "id": 5808689107,
      "lat": 15.4151862,
      "lon": 73.9888077
    },
    {
      "type": "node",
      "id": 5808689108,
      "lat": 15.4152143,
      "lon": 73.9888459
    },
    {
      "type": "node",
      "id": 5808689109,
      "lat": 15.4152553,
      "lon": 73.9888135
    },
    {
      "type": "node",
      "id": 5808689110,
      "lat": 15.4152198,
      "lon": 73.9887652
    },
    {
      "type": "node",
      "id": 5808689111,
      "lat": 15.4152633,
      "lon": 73.9887308
    },
    {
      "type": "node",
      "id": 5808689112,
      "lat": 15.4152955,
      "lon": 73.9887746
    },
    {
      "type": "node",
      "id": 5808689113,
      "lat": 15.4153114,
      "lon": 73.9887621
    },
    {
      "type": "node",
      "id": 5808689114,
      "lat": 15.4152721,
      "lon": 73.9887087
    },
    {
      "type": "node",
      "id": 5715189649,
      "lat": 15.420624,
      "lon": 73.9799673
    },
    {
      "type": "node",
      "id": 5715189650,
      "lat": 15.4206359,
      "lon": 73.9800182
    },
    {
      "type": "node",
      "id": 5715189651,
      "lat": 15.4207224,
      "lon": 73.9799964
    },
    {
      "type": "node",
      "id": 5715189652,
      "lat": 15.4207347,
      "lon": 73.980049
    },
    {
      "type": "node",
      "id": 5715189653,
      "lat": 15.4207633,
      "lon": 73.9800418
    },
    {
      "type": "node",
      "id": 5715189654,
      "lat": 15.420739,
      "lon": 73.9799383
    },
    {
      "type": "node",
      "id": 5715189655,
      "lat": 15.4205232,
      "lon": 73.9799765
    },
    {
      "type": "node",
      "id": 5715189656,
      "lat": 15.4205628,
      "lon": 73.9799714
    },
    {
      "type": "node",
      "id": 5715189657,
      "lat": 15.4205708,
      "lon": 73.9800372
    },
    {
      "type": "node",
      "id": 5715189658,
      "lat": 15.4205457,
      "lon": 73.9800405
    },
    {
      "type": "node",
      "id": 5715189659,
      "lat": 15.4205478,
      "lon": 73.9800573
    },
    {
      "type": "node",
      "id": 5715189660,
      "lat": 15.420576,
      "lon": 73.9800536
    },
    {
      "type": "node",
      "id": 5715189661,
      "lat": 15.420578,
      "lon": 73.9800706
    },
    {
      "type": "node",
      "id": 5715189662,
      "lat": 15.420568,
      "lon": 73.9800719
    },
    {
      "type": "node",
      "id": 5715189663,
      "lat": 15.4205717,
      "lon": 73.9801027
    },
    {
      "type": "node",
      "id": 5715189664,
      "lat": 15.420617,
      "lon": 73.9800968
    },
    {
      "type": "node",
      "id": 5715189665,
      "lat": 15.4206218,
      "lon": 73.980137
    },
    {
      "type": "node",
      "id": 5715189666,
      "lat": 15.4206767,
      "lon": 73.9801299
    },
    {
      "type": "node",
      "id": 5715189667,
      "lat": 15.420673,
      "lon": 73.9801
    },
    {
      "type": "node",
      "id": 5715189668,
      "lat": 15.4207333,
      "lon": 73.9800922
    },
    {
      "type": "node",
      "id": 5715189669,
      "lat": 15.4207352,
      "lon": 73.980108
    },
    {
      "type": "node",
      "id": 5715189670,
      "lat": 15.4207838,
      "lon": 73.9801017
    },
    {
      "type": "node",
      "id": 5715189671,
      "lat": 15.4207907,
      "lon": 73.9801589
    },
    {
      "type": "node",
      "id": 5715189672,
      "lat": 15.4208531,
      "lon": 73.9801508
    },
    {
      "type": "node",
      "id": 5715189673,
      "lat": 15.4208133,
      "lon": 73.9799048
    },
    {
      "type": "node",
      "id": 5715189674,
      "lat": 15.4207366,
      "lon": 73.9798496
    },
    {
      "type": "node",
      "id": 5715189675,
      "lat": 15.4205151,
      "lon": 73.9799087
    },
    {
      "type": "node",
      "id": 5715189676,
      "lat": 15.4200452,
      "lon": 73.9794611
    },
    {
      "type": "node",
      "id": 5715189677,
      "lat": 15.4199117,
      "lon": 73.9794311
    },
    {
      "type": "node",
      "id": 5715189678,
      "lat": 15.4199311,
      "lon": 73.97935
    },
    {
      "type": "node",
      "id": 5715189679,
      "lat": 15.4200743,
      "lon": 73.9793913
    },
    {
      "type": "node",
      "id": 5715189680,
      "lat": 15.4201166,
      "lon": 73.9793453
    },
    {
      "type": "node",
      "id": 5715189681,
      "lat": 15.4200668,
      "lon": 73.9795391
    },
    {
      "type": "node",
      "id": 5715189682,
      "lat": 15.4201838,
      "lon": 73.9795055
    },
    {
      "type": "node",
      "id": 5715189683,
      "lat": 15.4202045,
      "lon": 73.9794371
    },
    {
      "type": "node",
      "id": 5715189684,
      "lat": 15.4202776,
      "lon": 73.9792819
    },
    {
      "type": "node",
      "id": 5715189685,
      "lat": 15.4202653,
      "lon": 73.9792973
    },
    {
      "type": "node",
      "id": 5715189686,
      "lat": 15.4202911,
      "lon": 73.9793754
    },
    {
      "type": "node",
      "id": 5715189687,
      "lat": 15.420307,
      "lon": 73.9793791
    },
    {
      "type": "node",
      "id": 5715189688,
      "lat": 15.4203584,
      "lon": 73.9793225
    },
    {
      "type": "node",
      "id": 5715189689,
      "lat": 15.4203555,
      "lon": 73.979298
    },
    {
      "type": "node",
      "id": 5715189690,
      "lat": 15.4204498,
      "lon": 73.9793245
    },
    {
      "type": "node",
      "id": 5715189691,
      "lat": 15.420306,
      "lon": 73.9794743
    },
    {
      "type": "node",
      "id": 5715189692,
      "lat": 15.4202533,
      "lon": 73.979467
    },
    {
      "type": "node",
      "id": 5715189693,
      "lat": 15.4201913,
      "lon": 73.9792474
    },
    {
      "type": "node",
      "id": 5715189694,
      "lat": 15.4202359,
      "lon": 73.9791947
    },
    {
      "type": "node",
      "id": 5715189695,
      "lat": 15.420434,
      "lon": 73.9792527
    },
    {
      "type": "node",
      "id": 5715189696,
      "lat": 15.420275,
      "lon": 73.9796819
    },
    {
      "type": "node",
      "id": 5715189697,
      "lat": 15.4202585,
      "lon": 73.9796976
    },
    {
      "type": "node",
      "id": 5715189698,
      "lat": 15.4201764,
      "lon": 73.9796738
    },
    {
      "type": "node",
      "id": 5715189699,
      "lat": 15.4201719,
      "lon": 73.9796614
    },
    {
      "type": "node",
      "id": 5715189700,
      "lat": 15.4202313,
      "lon": 73.9795927
    },
    {
      "type": "node",
      "id": 5715189701,
      "lat": 15.420252,
      "lon": 73.9796017
    },
    {
      "type": "node",
      "id": 5715189702,
      "lat": 15.4202898,
      "lon": 73.979522
    },
    {
      "type": "node",
      "id": 5715189703,
      "lat": 15.420349,
      "lon": 73.9797255
    },
    {
      "type": "node",
      "id": 5715189704,
      "lat": 15.4203054,
      "lon": 73.9797778
    },
    {
      "type": "node",
      "id": 5715189705,
      "lat": 15.420104,
      "lon": 73.9797268
    },
    {
      "type": "node",
      "id": 5715189706,
      "lat": 15.4200895,
      "lon": 73.9796577
    },
    {
      "type": "node",
      "id": 5715189707,
      "lat": 15.4202372,
      "lon": 73.9794992
    },
    {
      "type": "node",
      "id": 5715189708,
      "lat": 15.4197779,
      "lon": 73.9796142
    },
    {
      "type": "node",
      "id": 5715189709,
      "lat": 15.4197953,
      "lon": 73.9796765
    },
    {
      "type": "node",
      "id": 5715189710,
      "lat": 15.4200119,
      "lon": 73.9797288
    },
    {
      "type": "node",
      "id": 5715189711,
      "lat": 15.4200423,
      "lon": 73.9796655
    },
    {
      "type": "node",
      "id": 5715189712,
      "lat": 15.4199928,
      "lon": 73.9794743
    },
    {
      "type": "node",
      "id": 5715189713,
      "lat": 15.4199363,
      "lon": 73.9794529
    },
    {
      "type": "node",
      "id": 5715189714,
      "lat": 15.4199702,
      "lon": 73.9796393
    },
    {
      "type": "node",
      "id": 5715189715,
      "lat": 15.4199515,
      "lon": 73.9796514
    },
    {
      "type": "node",
      "id": 5715189716,
      "lat": 15.4198723,
      "lon": 73.9796299
    },
    {
      "type": "node",
      "id": 5715189717,
      "lat": 15.4198723,
      "lon": 73.9796108
    },
    {
      "type": "node",
      "id": 5715189718,
      "lat": 15.4199311,
      "lon": 73.9795511
    },
    {
      "type": "node",
      "id": 5715189719,
      "lat": 15.4199502,
      "lon": 73.9795521
    },
    {
      "type": "node",
      "id": 5715189720,
      "lat": 15.4200681,
      "lon": 73.9791877
    },
    {
      "type": "node",
      "id": 5715193421,
      "lat": 15.4200746,
      "lon": 73.9792098
    },
    {
      "type": "node",
      "id": 5715193422,
      "lat": 15.4200203,
      "lon": 73.9792661
    },
    {
      "type": "node",
      "id": 5715193423,
      "lat": 15.4200022,
      "lon": 73.9792621
    },
    {
      "type": "node",
      "id": 5715193424,
      "lat": 15.419986,
      "lon": 73.9791837
    },
    {
      "type": "node",
      "id": 5715193425,
      "lat": 15.4200041,
      "lon": 73.9791682
    },
    {
      "type": "node",
      "id": 5715193426,
      "lat": 15.4199544,
      "lon": 73.9790858
    },
    {
      "type": "node",
      "id": 5715193427,
      "lat": 15.4199014,
      "lon": 73.9791327
    },
    {
      "type": "node",
      "id": 5715193428,
      "lat": 15.4199595,
      "lon": 73.9793533
    },
    {
      "type": "node",
      "id": 5715193429,
      "lat": 15.4200132,
      "lon": 73.9793654
    },
    {
      "type": "node",
      "id": 5715193430,
      "lat": 15.4201677,
      "lon": 73.9792192
    },
    {
      "type": "node",
      "id": 5715193431,
      "lat": 15.4201457,
      "lon": 73.9791421
    },
    {
      "type": "node",
      "id": 5810338252,
      "lat": 15.4236549,
      "lon": 73.9814098
    },
    {
      "type": "node",
      "id": 5810338253,
      "lat": 15.4236985,
      "lon": 73.9815008
    },
    {
      "type": "node",
      "id": 5810338254,
      "lat": 15.4237333,
      "lon": 73.9814828
    },
    {
      "type": "node",
      "id": 5810338255,
      "lat": 15.4237613,
      "lon": 73.9815412
    },
    {
      "type": "node",
      "id": 5810338256,
      "lat": 15.423543,
      "lon": 73.9816537
    },
    {
      "type": "node",
      "id": 5810338257,
      "lat": 15.4235434,
      "lon": 73.9816881
    },
    {
      "type": "node",
      "id": 5810338258,
      "lat": 15.4235986,
      "lon": 73.9816875
    },
    {
      "type": "node",
      "id": 5810338259,
      "lat": 15.4236,
      "lon": 73.9818281
    },
    {
      "type": "node",
      "id": 5810338260,
      "lat": 15.4233749,
      "lon": 73.9818305
    },
    {
      "type": "node",
      "id": 5810338261,
      "lat": 15.4233736,
      "lon": 73.9816979
    },
    {
      "type": "node",
      "id": 5810338262,
      "lat": 15.4234451,
      "lon": 73.9816971
    },
    {
      "type": "node",
      "id": 5810338263,
      "lat": 15.4234448,
      "lon": 73.9816617
    },
    {
      "type": "node",
      "id": 5810338264,
      "lat": 15.4232019,
      "lon": 73.981558
    },
    {
      "type": "node",
      "id": 5810338265,
      "lat": 15.4232326,
      "lon": 73.9814807
    },
    {
      "type": "node",
      "id": 5810338266,
      "lat": 15.4232806,
      "lon": 73.9815012
    },
    {
      "type": "node",
      "id": 5810338267,
      "lat": 15.4233093,
      "lon": 73.9814286
    },
    {
      "type": "node",
      "id": 5810338268,
      "lat": 15.4234784,
      "lon": 73.9815008
    },
    {
      "type": "node",
      "id": 5810338277,
      "lat": 15.423896,
      "lon": 73.9813852
    },
    {
      "type": "node",
      "id": 5810338279,
      "lat": 15.4238746,
      "lon": 73.9813229
    },
    {
      "type": "node",
      "id": 5810338281,
      "lat": 15.4238738,
      "lon": 73.9809865
    },
    {
      "type": "node",
      "id": 5810338283,
      "lat": 15.4238798,
      "lon": 73.9808976
    },
    {
      "type": "node",
      "id": 5810338313,
      "lat": 15.423801,
      "lon": 73.9822845
    },
    {
      "type": "node",
      "id": 5810338314,
      "lat": 15.4236824,
      "lon": 73.9825199
    },
    {
      "type": "node",
      "id": 5810338315,
      "lat": 15.4238067,
      "lon": 73.9827406
    },
    {
      "type": "node",
      "id": 5810338316,
      "lat": 15.4237118,
      "lon": 73.9827982
    },
    {
      "type": "node",
      "id": 5810338317,
      "lat": 15.4235749,
      "lon": 73.9825553
    },
    {
      "type": "node",
      "id": 5810338318,
      "lat": 15.4235545,
      "lon": 73.9825554
    },
    {
      "type": "node",
      "id": 5810338319,
      "lat": 15.4235549,
      "lon": 73.9826983
    },
    {
      "type": "node",
      "id": 5810338320,
      "lat": 15.4236181,
      "lon": 73.9826981
    },
    {
      "type": "node",
      "id": 5810338321,
      "lat": 15.4236188,
      "lon": 73.982923
    },
    {
      "type": "node",
      "id": 5810338322,
      "lat": 15.4234469,
      "lon": 73.9829235
    },
    {
      "type": "node",
      "id": 5810338323,
      "lat": 15.4234463,
      "lon": 73.9826965
    },
    {
      "type": "node",
      "id": 5810338324,
      "lat": 15.4235024,
      "lon": 73.9826963
    },
    {
      "type": "node",
      "id": 5810338325,
      "lat": 15.423502,
      "lon": 73.982557
    },
    {
      "type": "node",
      "id": 5810338326,
      "lat": 15.4234845,
      "lon": 73.9825571
    },
    {
      "type": "node",
      "id": 5810338327,
      "lat": 15.4233439,
      "lon": 73.9828197
    },
    {
      "type": "node",
      "id": 5810338328,
      "lat": 15.4232471,
      "lon": 73.9827639
    },
    {
      "type": "node",
      "id": 5810338329,
      "lat": 15.4233702,
      "lon": 73.9825341
    },
    {
      "type": "node",
      "id": 5810338330,
      "lat": 15.4232365,
      "lon": 73.9823042
    },
    {
      "type": "node",
      "id": 5810338331,
      "lat": 15.423341,
      "lon": 73.9822388
    },
    {
      "type": "node",
      "id": 5810338332,
      "lat": 15.4234674,
      "lon": 73.9824562
    },
    {
      "type": "node",
      "id": 5810338333,
      "lat": 15.4235817,
      "lon": 73.9824509
    },
    {
      "type": "node",
      "id": 5810338334,
      "lat": 15.4236946,
      "lon": 73.9822268
    },
    {
      "type": "node",
      "id": 10892561642,
      "lat": 15.4225506,
      "lon": 73.9821808
    },
    {
      "type": "node",
      "id": 10892561643,
      "lat": 15.4224644,
      "lon": 73.9821915
    },
    {
      "type": "node",
      "id": 10892561644,
      "lat": 15.4224886,
      "lon": 73.9823775
    },
    {
      "type": "node",
      "id": 10892561645,
      "lat": 15.4224024,
      "lon": 73.9823918
    },
    {
      "type": "node",
      "id": 10892561646,
      "lat": 15.4223748,
      "lon": 73.9821879
    },
    {
      "type": "node",
      "id": 10892561647,
      "lat": 15.422261,
      "lon": 73.9821987
    },
    {
      "type": "node",
      "id": 10892561648,
      "lat": 15.4222852,
      "lon": 73.9825456
    },
    {
      "type": "node",
      "id": 10892561649,
      "lat": 15.4225989,
      "lon": 73.9825241
    },
    {
      "type": "node",
      "id": 10892561650,
      "lat": 15.4225954,
      "lon": 73.9824597
    },
    {
      "type": "node",
      "id": 10892561651,
      "lat": 15.4226265,
      "lon": 73.9824347
    },
    {
      "type": "node",
      "id": 10892561652,
      "lat": 15.4225851,
      "lon": 73.9821557
    },
    {
      "type": "node",
      "id": 10892561655,
      "lat": 15.4223394,
      "lon": 73.9825419
    },
    {
      "type": "node",
      "id": 10892561656,
      "lat": 15.4223075,
      "lon": 73.9825652
    },
    {
      "type": "node",
      "id": 10892561657,
      "lat": 15.4222558,
      "lon": 73.9825743
    },
    {
      "type": "node",
      "id": 10892561658,
      "lat": 15.4222469,
      "lon": 73.9825412
    },
    {
      "type": "node",
      "id": 10892561659,
      "lat": 15.4220673,
      "lon": 73.9825663
    },
    {
      "type": "node",
      "id": 10892561660,
      "lat": 15.4220717,
      "lon": 73.9826052
    },
    {
      "type": "node",
      "id": 10892561661,
      "lat": 15.4220552,
      "lon": 73.9826098
    },
    {
      "type": "node",
      "id": 10892561662,
      "lat": 15.4220464,
      "lon": 73.9825755
    },
    {
      "type": "node",
      "id": 10892561663,
      "lat": 15.4220034,
      "lon": 73.9825812
    },
    {
      "type": "node",
      "id": 10892561664,
      "lat": 15.4220034,
      "lon": 73.9825972
    },
    {
      "type": "node",
      "id": 10892561665,
      "lat": 15.4219758,
      "lon": 73.9825995
    },
    {
      "type": "node",
      "id": 10892561666,
      "lat": 15.4219869,
      "lon": 73.9826967
    },
    {
      "type": "node",
      "id": 10892561667,
      "lat": 15.4221987,
      "lon": 73.9826606
    },
    {
      "type": "node",
      "id": 10892561668,
      "lat": 15.422194,
      "lon": 73.9826944
    },
    {
      "type": "node",
      "id": 10892561669,
      "lat": 15.4222139,
      "lon": 73.9826864
    },
    {
      "type": "node",
      "id": 10892561670,
      "lat": 15.4222238,
      "lon": 73.9827504
    },
    {
      "type": "node",
      "id": 10892561671,
      "lat": 15.4222018,
      "lon": 73.9827755
    },
    {
      "type": "node",
      "id": 10892561672,
      "lat": 15.4219836,
      "lon": 73.9828213
    },
    {
      "type": "node",
      "id": 10892561673,
      "lat": 15.4220692,
      "lon": 73.98291
    },
    {
      "type": "node",
      "id": 10892561674,
      "lat": 15.4222899,
      "lon": 73.9828739
    },
    {
      "type": "node",
      "id": 10892561675,
      "lat": 15.4222855,
      "lon": 73.982835
    },
    {
      "type": "node",
      "id": 10892561676,
      "lat": 15.4223472,
      "lon": 73.982827
    },
    {
      "type": "node",
      "id": 10892641629,
      "lat": 15.4220477,
      "lon": 73.982688
    },
    {
      "type": "node",
      "id": 10988315039,
      "lat": 15.422674,
      "lon": 73.9828462
    },
    {
      "type": "node",
      "id": 10988315040,
      "lat": 15.4226473,
      "lon": 73.9828503
    },
    {
      "type": "node",
      "id": 10988315041,
      "lat": 15.4226426,
      "lon": 73.9827885
    },
    {
      "type": "node",
      "id": 10988315042,
      "lat": 15.4223863,
      "lon": 73.9828381
    },
    {
      "type": "node",
      "id": 10988315043,
      "lat": 15.4223863,
      "lon": 73.9828113
    },
    {
      "type": "node",
      "id": 10988315044,
      "lat": 15.4223589,
      "lon": 73.9828145
    },
    {
      "type": "node",
      "id": 10988315045,
      "lat": 15.4223495,
      "lon": 73.9828454
    },
    {
      "type": "node",
      "id": 10988315046,
      "lat": 15.4223103,
      "lon": 73.9828487
    },
    {
      "type": "node",
      "id": 10988315047,
      "lat": 15.4223173,
      "lon": 73.9828991
    },
    {
      "type": "node",
      "id": 10988315048,
      "lat": 15.4222828,
      "lon": 73.9829121
    },
    {
      "type": "node",
      "id": 10988315049,
      "lat": 15.4222907,
      "lon": 73.9829853
    },
    {
      "type": "node",
      "id": 10988315050,
      "lat": 15.4223369,
      "lon": 73.9829804
    },
    {
      "type": "node",
      "id": 10988315051,
      "lat": 15.4223644,
      "lon": 73.9831772
    },
    {
      "type": "node",
      "id": 10988315052,
      "lat": 15.4224796,
      "lon": 73.9831674
    },
    {
      "type": "node",
      "id": 10988315053,
      "lat": 15.4224655,
      "lon": 73.982969
    },
    {
      "type": "node",
      "id": 10988315054,
      "lat": 15.4225595,
      "lon": 73.9829568
    },
    {
      "type": "node",
      "id": 10988315055,
      "lat": 15.422583,
      "lon": 73.9831837
    },
    {
      "type": "node",
      "id": 10988315056,
      "lat": 15.4227139,
      "lon": 73.9831251
    },
    {
      "type": "node",
      "id": 10988315057,
      "lat": 15.4226873,
      "lon": 73.9828316
    },
    {
      "type": "node",
      "id": 10988315058,
      "lat": 15.4231324,
      "lon": 73.9831221
    },
    {
      "type": "node",
      "id": 10988315059,
      "lat": 15.4231654,
      "lon": 73.9834049
    },
    {
      "type": "node",
      "id": 10988315060,
      "lat": 15.4231317,
      "lon": 73.9834488
    },
    {
      "type": "node",
      "id": 10988315061,
      "lat": 15.4230356,
      "lon": 73.9834644
    },
    {
      "type": "node",
      "id": 10988315062,
      "lat": 15.4229982,
      "lon": 73.9832471
    },
    {
      "type": "node",
      "id": 10988315063,
      "lat": 15.4229308,
      "lon": 73.9832367
    },
    {
      "type": "node",
      "id": 10988315064,
      "lat": 15.4229107,
      "lon": 73.9832545
    },
    {
      "type": "node",
      "id": 10988315065,
      "lat": 15.4229243,
      "lon": 73.983457
    },
    {
      "type": "node",
      "id": 10988315066,
      "lat": 15.422816,
      "lon": 73.9834711
    },
    {
      "type": "node",
      "id": 10988315067,
      "lat": 15.4227809,
      "lon": 73.9832054
    },
    {
      "type": "node",
      "id": 10988315068,
      "lat": 15.4228117,
      "lon": 73.9831935
    },
    {
      "type": "node",
      "id": 10988315069,
      "lat": 15.4227952,
      "lon": 73.9831503
    },
    {
      "type": "node",
      "id": 10988315070,
      "lat": 15.4228246,
      "lon": 73.9831243
    },
    {
      "type": "node",
      "id": 10988315071,
      "lat": 15.4230643,
      "lon": 73.9830923
    },
    {
      "type": "node",
      "id": 10988315072,
      "lat": 15.4230973,
      "lon": 73.9830588
    },
    {
      "type": "node",
      "id": 10988315073,
      "lat": 15.4231001,
      "lon": 73.9831094
    },
    {
      "type": "node",
      "id": 10988315074,
      "lat": 15.4231389,
      "lon": 73.983096
    },
    {
      "type": "node",
      "id": 5810338269,
      "lat": 15.4242769,
      "lon": 73.9809946
    },
    {
      "type": "node",
      "id": 5810338270,
      "lat": 15.4242885,
      "lon": 73.9812074
    },
    {
      "type": "node",
      "id": 5810338271,
      "lat": 15.424164,
      "lon": 73.9812147
    },
    {
      "type": "node",
      "id": 5810338272,
      "lat": 15.4241611,
      "lon": 73.9811605
    },
    {
      "type": "node",
      "id": 5810338273,
      "lat": 15.4241286,
      "lon": 73.9811624
    },
    {
      "type": "node",
      "id": 5810338274,
      "lat": 15.4240489,
      "lon": 73.9813451
    },
    {
      "type": "node",
      "id": 5810338275,
      "lat": 15.4240264,
      "lon": 73.9813346
    },
    {
      "type": "node",
      "id": 5810338276,
      "lat": 15.4239859,
      "lon": 73.9814274
    },
    {
      "type": "node",
      "id": 5810338278,
      "lat": 15.4239149,
      "lon": 73.9813418
    },
    {
      "type": "node",
      "id": 5810338280,
      "lat": 15.4239632,
      "lon": 73.9811199
    },
    {
      "type": "node",
      "id": 5810338282,
      "lat": 15.423918,
      "lon": 73.9809546
    },
    {
      "type": "node",
      "id": 5810338284,
      "lat": 15.4239431,
      "lon": 73.980852
    },
    {
      "type": "node",
      "id": 5810338285,
      "lat": 15.4239864,
      "lon": 73.9809167
    },
    {
      "type": "node",
      "id": 5810338286,
      "lat": 15.4240143,
      "lon": 73.9808966
    },
    {
      "type": "node",
      "id": 5810338287,
      "lat": 15.4241235,
      "lon": 73.9810597
    },
    {
      "type": "node",
      "id": 5810338288,
      "lat": 15.4241476,
      "lon": 73.9810583
    },
    {
      "type": "node",
      "id": 5810338289,
      "lat": 15.4241446,
      "lon": 73.9810024
    },
    {
      "type": "node",
      "id": 5810338290,
      "lat": 15.4240809,
      "lon": 73.9820239
    },
    {
      "type": "node",
      "id": 5810338291,
      "lat": 15.4241655,
      "lon": 73.9819823
    },
    {
      "type": "node",
      "id": 5810338292,
      "lat": 15.4241819,
      "lon": 73.9820916
    },
    {
      "type": "node",
      "id": 5810338293,
      "lat": 15.4242145,
      "lon": 73.9820732
    },
    {
      "type": "node",
      "id": 5810338294,
      "lat": 15.4242502,
      "lon": 73.9822673
    },
    {
      "type": "node",
      "id": 5810338295,
      "lat": 15.4242714,
      "lon": 73.9822756
    },
    {
      "type": "node",
      "id": 5810338296,
      "lat": 15.4242872,
      "lon": 73.9822321
    },
    {
      "type": "node",
      "id": 5810338297,
      "lat": 15.4244045,
      "lon": 73.9822781
    },
    {
      "type": "node",
      "id": 5810338298,
      "lat": 15.4243514,
      "lon": 73.9824239
    },
    {
      "type": "node",
      "id": 5810338299,
      "lat": 15.4243683,
      "lon": 73.9824305
    },
    {
      "type": "node",
      "id": 5810338300,
      "lat": 15.4243503,
      "lon": 73.9824799
    },
    {
      "type": "node",
      "id": 5810338301,
      "lat": 15.4242263,
      "lon": 73.9824314
    },
    {
      "type": "node",
      "id": 5810338302,
      "lat": 15.4242449,
      "lon": 73.9823801
    },
    {
      "type": "node",
      "id": 5810338303,
      "lat": 15.4242205,
      "lon": 73.9823705
    },
    {
      "type": "node",
      "id": 5810338304,
      "lat": 15.4240788,
      "lon": 73.9824963
    },
    {
      "type": "node",
      "id": 5810338305,
      "lat": 15.4240595,
      "lon": 73.9824729
    },
    {
      "type": "node",
      "id": 5810338306,
      "lat": 15.4239891,
      "lon": 73.9825355
    },
    {
      "type": "node",
      "id": 5810338307,
      "lat": 15.4239341,
      "lon": 73.9824688
    },
    {
      "type": "node",
      "id": 5810338308,
      "lat": 15.423965,
      "lon": 73.9824413
    },
    {
      "type": "node",
      "id": 5810338309,
      "lat": 15.4239472,
      "lon": 73.9824013
    },
    {
      "type": "node",
      "id": 5810338310,
      "lat": 15.4240824,
      "lon": 73.9822719
    },
    {
      "type": "node",
      "id": 5810338311,
      "lat": 15.4240454,
      "lon": 73.9820692
    },
    {
      "type": "node",
      "id": 5810338312,
      "lat": 15.4240876,
      "lon": 73.9820609
    },
    {
      "type": "node",
      "id": 1808788525,
      "lat": 15.4409667,
      "lon": 73.9736594
    },
    {
      "type": "node",
      "id": 1808788527,
      "lat": 15.4408529,
      "lon": 73.9734556
    },
    {
      "type": "node",
      "id": 1808788529,
      "lat": 15.4407702,
      "lon": 73.9737855
    },
    {
      "type": "node",
      "id": 1808788531,
      "lat": 15.4406461,
      "lon": 73.9735682
    },
    {
      "type": "way",
      "id": 601302468,
      "nodes": [
        5715189654,
        5715189653,
        5715189652,
        5715189651,
        5715189650,
        5715189649,
        5715189654
      ]
    },
    {
      "type": "way",
      "id": 601302469,
      "nodes": [
        5715189675,
        5715189674,
        5715189673,
        5715189672,
        5715189671,
        5715189670,
        5715189669,
        5715189668,
        5715189667,
        5715189666,
        5715189665,
        5715189664,
        5715189663,
        5715189662,
        5715189661,
        5715189660,
        5715189659,
        5715189658,
        5715189657,
        5715189656,
        5715189655,
        5715189675
      ]
    },
    {
      "type": "way",
      "id": 601302470,
      "nodes": [
        5715189676,
        5715189677,
        5715189678,
        5715189679,
        5715189680,
        5715189683,
        5715189682,
        5715189681,
        5715189676
      ]
    },
    {
      "type": "way",
      "id": 601302471,
      "nodes": [
        5715189689,
        5715189688,
        5715189687,
        5715189686,
        5715189685,
        5715189684,
        5715189689
      ]
    },
    {
      "type": "way",
      "id": 601302472,
      "nodes": [
        5715189695,
        5715189694,
        5715189693,
        5715189692,
        5715189691,
        5715189690,
        5715189695
      ]
    },
    {
      "type": "way",
      "id": 601302473,
      "nodes": [
        5715189701,
        5715189700,
        5715189699,
        5715189698,
        5715189697,
        5715189696,
        5715189701
      ]
    },
    {
      "type": "way",
      "id": 601302474,
      "nodes": [
        5715189707,
        5715189706,
        5715189705,
        5715189704,
        5715189703,
        5715189702,
        5715189707
      ]
    },
    {
      "type": "way",
      "id": 601302475,
      "nodes": [
        5715189713,
        5715189712,
        5715189711,
        5715189710,
        5715189709,
        5715189708,
        5715189713
      ]
    },
    {
      "type": "way",
      "id": 601302476,
      "nodes": [
        5715189719,
        5715189718,
        5715189717,
        5715189716,
        5715189715,
        5715189714,
        5715189719
      ]
    },
    {
      "type": "way",
      "id": 601302477,
      "nodes": [
        5715193425,
        5715193424,
        5715193423,
        5715193422,
        5715193421,
        5715189720,
        5715193425
      ]
    },
    {
      "type": "way",
      "id": 601302478,
      "nodes": [
        5715193431,
        5715193430,
        5715193429,
        5715193428,
        5715193427,
        5715193426,
        5715193431
      ]
    }
  ]
}